{
  "contentTypes": [
    {
      "sys": {
        "space": {
          "sys": {
            "type": "Link",
            "linkType": "Space",
            "id": "2ehq0rlwazzo"
          }
        },
        "id": "person",
        "type": "ContentType",
        "createdAt": "2020-12-15T04:31:25.933Z",
        "updatedAt": "2020-12-15T04:31:27.218Z",
        "environment": {
          "sys": {
            "id": "master",
            "type": "Link",
            "linkType": "Environment"
          }
        },
        "publishedVersion": 1,
        "publishedAt": "2020-12-15T04:31:27.218Z",
        "firstPublishedAt": "2020-12-15T04:31:27.218Z",
        "createdBy": {
          "sys": {
            "type": "Link",
            "linkType": "User",
            "id": "6Jo86L3mtfRghoYHVI37HW"
          }
        },
        "updatedBy": {
          "sys": {
            "type": "Link",
            "linkType": "User",
            "id": "6Jo86L3mtfRghoYHVI37HW"
          }
        },
        "publishedCounter": 1,
        "version": 2,
        "publishedBy": {
          "sys": {
            "type": "Link",
            "linkType": "User",
            "id": "6Jo86L3mtfRghoYHVI37HW"
          }
        }
      },
      "displayField": "name",
      "name": "Person",
      "description": null,
      "fields": [
        {
          "id": "name",
          "name": "Name",
          "type": "Symbol",
          "localized": false,
          "required": true,
          "validations": [
          ],
          "disabled": false,
          "omitted": false
        },
        {
          "id": "title",
          "name": "Title",
          "type": "Symbol",
          "localized": false,
          "required": true,
          "validations": [
          ],
          "disabled": false,
          "omitted": false
        },
        {
          "id": "company",
          "name": "Company",
          "type": "Symbol",
          "localized": false,
          "required": true,
          "validations": [
          ],
          "disabled": false,
          "omitted": false
        },
        {
          "id": "shortBio",
          "name": "Short Bio",
          "type": "Text",
          "localized": false,
          "required": true,
          "validations": [
          ],
          "disabled": false,
          "omitted": false
        },
        {
          "id": "email",
          "name": "Email",
          "type": "Symbol",
          "localized": false,
          "required": false,
          "validations": [
          ],
          "disabled": false,
          "omitted": false
        },
        {
          "id": "phone",
          "name": "Phone",
          "type": "Symbol",
          "localized": false,
          "required": false,
          "validations": [
          ],
          "disabled": false,
          "omitted": false
        },
        {
          "id": "facebook",
          "name": "Facebook",
          "type": "Symbol",
          "localized": false,
          "required": false,
          "validations": [
          ],
          "disabled": false,
          "omitted": false
        },
        {
          "id": "twitter",
          "name": "Twitter",
          "type": "Symbol",
          "localized": false,
          "required": false,
          "validations": [
          ],
          "disabled": false,
          "omitted": false
        },
        {
          "id": "github",
          "name": "Github",
          "type": "Symbol",
          "localized": false,
          "required": false,
          "validations": [
          ],
          "disabled": false,
          "omitted": false
        },
        {
          "id": "image",
          "name": "Image",
          "type": "Link",
          "localized": false,
          "required": false,
          "validations": [
          ],
          "disabled": false,
          "omitted": false,
          "linkType": "Asset"
        }
      ]
    }
  ]
}